str2int.py
str2int-1.0.4.dist-info/METADATA
str2int-1.0.4.dist-info/WHEEL
str2int-1.0.4.dist-info/top_level.txt
str2int-1.0.4.dist-info/RECORD
