Metadata-Version: 2.1
Name: str2int
Version: 1.0.4
Summary: A simple module to suck intagers out of strings
Home-page: https://github.com/anishgorakavi787809/str2int
Author: Anish Gorakavi
Author-email: anish.gorakavi@gmail.com
License: UNKNOWN
Platform: UNKNOWN
Classifier: Programming Language :: Python :: 3
Classifier: License :: OSI Approved :: MIT License
Classifier: Operating System :: OS Independent
